LICENSE
README.md
setup.py
hopfenmatrix/__init__.py
hopfenmatrix/callbacks.py
hopfenmatrix/config.py
hopfenmatrix/logging.py
hopfenmatrix/matrix.py
hopfenmatrix/run.py
hopfenmatrix.egg-info/PKG-INFO
hopfenmatrix.egg-info/SOURCES.txt
hopfenmatrix.egg-info/dependency_links.txt
hopfenmatrix.egg-info/requires.txt
hopfenmatrix.egg-info/top_level.txt