Metadata-Version: 2.1
Name: hopfenmatrix
Version: 0.4.7
Summary: A library to make matrix-nio easier
Home-page: https://github.com/hopfenspace/hopfenmatrix/
Author: Wolfgang Fischer, Niklas Pfister
Author-email: kontakt@omikron.dev
License: UNKNOWN
Platform: UNKNOWN
Classifier: Programming Language :: Python :: 3
Classifier: License :: OSI Approved :: GNU General Public License v2 or later (GPLv2+)
Classifier: Operating System :: OS Independent
Requires-Python: >=3.6
License-File: LICENSE
